gen_worker/__init__.py
gen_worker/backends.py
gen_worker/decorators.py
gen_worker/discover.py
gen_worker/downloader.py
gen_worker/entrypoint.py
gen_worker/errors.py
gen_worker/injection.py
gen_worker/model_cache.py
gen_worker/model_interface.py
gen_worker/pipeline_loader.py
gen_worker/project_validation.py
gen_worker/types.py
gen_worker/worker.py
gen_worker/pb/__init__.py
gen_worker/pb/frontend_pb2.py
gen_worker/pb/frontend_pb2_grpc.py
gen_worker/pb/worker_scheduler_pb2.py
gen_worker/pb/worker_scheduler_pb2_grpc.py
gen_worker/testing/__init__.py
gen_worker/testing/stub_manager.py
gen_worker-0.2.1.dist-info/METADATA
gen_worker-0.2.1.dist-info/WHEEL
gen_worker-0.2.1.dist-info/licenses/LICENSE
gen_worker-0.2.1.dist-info/RECORD
