Metadata-Version: 2.4
Name: gen-worker
Version: 0.2.1
Summary: A library used to build custom endpoints in Cozy Creator's serverless function platform.
Project-URL: Homepage, https://github.com/cozy-creator/python-gen-worker
Project-URL: Repository, https://github.com/cozy-creator/python-gen-worker
Project-URL: Issues, https://github.com/cozy-creator/python-gen-worker/issues
Author-email: Paul Fidika <paul@fidika.com>
License-Expression: MIT
License-File: LICENSE
Keywords: ai,cozy,inference,ml,serverless
Classifier: Development Status :: 4 - Beta
Classifier: Intended Audience :: Developers
Classifier: License :: OSI Approved :: MIT License
Classifier: Programming Language :: Python :: 3
Classifier: Programming Language :: Python :: 3.11
Classifier: Programming Language :: Python :: 3.12
Classifier: Programming Language :: Python :: 3.13
Classifier: Topic :: Scientific/Engineering :: Artificial Intelligence
Requires-Python: >=3.11
Requires-Dist: aiohttp>=3.11.14
Requires-Dist: backoff>=2.2.1
Requires-Dist: grpcio>=1.71.0
Requires-Dist: msgspec>=0.18.6
Requires-Dist: protobuf>=6.30.0
Requires-Dist: psutil>=7.0.0
Requires-Dist: pyjwt[crypto]>=2.8.0
Requires-Dist: tqdm>=4.66.0
Provides-Extra: dev
Requires-Dist: grpcio-tools>=1.71.0; extra == 'dev'
Requires-Dist: mypy>=1.10.0; extra == 'dev'
Requires-Dist: pytest>=9.0.0; extra == 'dev'
Provides-Extra: torch
Requires-Dist: flashpack>=0.1.2; extra == 'torch'
Requires-Dist: numpy>=1.26.0; extra == 'torch'
Requires-Dist: safetensors>=0.4.3; extra == 'torch'
Requires-Dist: torch>=2.6.0; extra == 'torch'
Requires-Dist: torchaudio>=2.6.0; extra == 'torch'
Requires-Dist: torchvision>=0.21.0; extra == 'torch'
